bloqade/lanes/__init__.py
bloqade/lanes/_prelude.py
bloqade/lanes/logical_mvp.py
bloqade/lanes/noise_model.py
bloqade/lanes/prelude.py
bloqade/lanes/transform.py
bloqade/lanes/types.py
bloqade/lanes/upstream.py
bloqade/lanes/visualize.py
bloqade/lanes/analysis/atom/__init__.py
bloqade/lanes/analysis/atom/_visitor.py
bloqade/lanes/analysis/atom/_visitor.pyi
bloqade/lanes/analysis/atom/analysis.py
bloqade/lanes/analysis/atom/atom_state_data.py
bloqade/lanes/analysis/atom/impl.py
bloqade/lanes/analysis/atom/lattice.py
bloqade/lanes/analysis/layout/__init__.py
bloqade/lanes/analysis/layout/analysis.py
bloqade/lanes/analysis/placement/__init__.py
bloqade/lanes/analysis/placement/analysis.py
bloqade/lanes/analysis/placement/lattice.py
bloqade/lanes/analysis/placement/strategy.py
bloqade/lanes/arch/__init__.py
bloqade/lanes/arch/gemini/impls.py
bloqade/lanes/arch/gemini/logical/__init__.py
bloqade/lanes/arch/gemini/logical/rewrite.py
bloqade/lanes/arch/gemini/logical/spec.py
bloqade/lanes/arch/gemini/logical/stmts.py
bloqade/lanes/arch/gemini/logical/upstream.py
bloqade/lanes/arch/gemini/logical/validation.py
bloqade/lanes/dialects/__init__.py
bloqade/lanes/dialects/move.py
bloqade/lanes/dialects/place.py
bloqade/lanes/heuristics/__init__.py
bloqade/lanes/heuristics/fixed.py
bloqade/lanes/layout/__init__.py
bloqade/lanes/layout/arch.py
bloqade/lanes/layout/encoding.py
bloqade/lanes/layout/numpy_compat.py
bloqade/lanes/layout/path.py
bloqade/lanes/layout/word.py
bloqade/lanes/rewrite/__init__.py
bloqade/lanes/rewrite/circuit2place.py
bloqade/lanes/rewrite/place2move.py
bloqade/lanes/rewrite/state.py
bloqade/lanes/rewrite/transversal.py
bloqade/lanes/rewrite/utils.py
bloqade/lanes/rewrite/move2squin/__init__.py
bloqade/lanes/rewrite/move2squin/base.py
bloqade/lanes/rewrite/move2squin/gates.py
bloqade/lanes/rewrite/move2squin/noise.py
bloqade/lanes/validation/__init__.py
bloqade/lanes/validation/address.py
bloqade_lanes-0.3.3.dist-info/METADATA
bloqade_lanes-0.3.3.dist-info/WHEEL
bloqade_lanes-0.3.3.dist-info/licenses/LICENSE
bloqade_lanes-0.3.3.dist-info/RECORD
