Metadata-Version: 2.4
Name: bloqade-lanes
Version: 0.3.3
Summary: Components for defining and manipulating lane-based structures in Bloqade for neutral atom quantum computing.
Author-email: Phillip Weinberg <pweinberg@quera.com>
License-File: LICENSE
Requires-Python: >=3.10
Requires-Dist: bloqade-circuit[cirq,qasm2]~=0.11.0
Requires-Dist: bloqade-geometry~=0.5.0
Requires-Dist: deprecated>=1.3.1
Requires-Dist: kirin-toolchain~=0.22.6
Requires-Dist: numpy>=2.2.6
Requires-Dist: rustworkx>=0.17.1
Provides-Extra: visualization
Requires-Dist: matplotlib>=3.9.4; extra == 'visualization'
Requires-Dist: scipy>=1.15.3; extra == 'visualization'
